logqbit/__init__.py
logqbit/assets/browser.svg
logqbit/assets/live_plotter.svg
logqbit/browser.py
logqbit/cli.py
logqbit/live_plotter.py
logqbit/logfolder.py
logqbit/metadata.py
logqbit/misc/svg2ico.py
logqbit/registry.py
logqbit/templates/move_from_labrad.py
logqbit-0.2.5.dist-info/WHEEL
logqbit-0.2.5.dist-info/entry_points.txt
logqbit-0.2.5.dist-info/METADATA
logqbit-0.2.5.dist-info/RECORD
