Metadata-Version: 2.3
Name: logqbit
Version: 0.2.5
Summary: Simple data logger and live plotter for lab-scale experiments.
Requires-Dist: numpy>=2.3.3
Requires-Dist: pandas>=2.3.3
Requires-Dist: pyarrow>=21.0.0
Requires-Dist: pyqtgraph>=0.13.7
Requires-Dist: pyside6>=6.9.3
Requires-Dist: ruamel-yaml>=0.18.15
Requires-Dist: send2trash>=1.8.3
Requires-Dist: tqdm>=4.67.1
Requires-Dist: typing-extensions>=4.15.0
Requires-Dist: pylabrad>=0.98.3 ; extra == 'labrad'
Requires-Python: >=3.11
Project-URL: Homepage, https://github.com/Qiujv/logqbit
Provides-Extra: labrad
